static_compressor/__init__.py
static_compressor/apps.py
static_compressor/compressors.py
static_compressor/middleware.py
static_compressor/mixin.py
static_compressor/staticfiles_storage.py
static_compressor/management/__init__.py
static_compressor/management/__pycache__/__init__.cpython-37.pyc
static_compressor/management/commands/collectstatic_compress.py
static_compressor/management/commands/__pycache__/collectstatic_compress.cpython-37.pyc
static_compressor/management/commands/__pycache__/collectstatic_compressed.cpython-37.pyc
static_compressor/management/commands/__pycache__/collectstaticcompressed.cpython-37.pyc
static_compressor/migrations/__init__.py
django_static_class_minifier-0.2.3.dist-info/LICENSE
django_static_class_minifier-0.2.3.dist-info/METADATA
django_static_class_minifier-0.2.3.dist-info/WHEEL
django_static_class_minifier-0.2.3.dist-info/top_level.txt
django_static_class_minifier-0.2.3.dist-info/RECORD
