Metadata-Version: 2.1
Name: django-static-class-minifier
Version: 0.2.3
Summary: The class minifier package shortens the class name in the DOM to gibberish characters.
Home-page: https://github.com/Navaneeth-Nagesh/django-static-class-minifier
Author: Navaneeth Nagesh
Author-email: navaneethnagesh56@gmail.com
License: MIT
Keywords: Django,class-minifier,compressor,pre-processor
Platform: UNKNOWN
Classifier: Development Status :: 5 - Production/Stable
Classifier: Environment :: Web Environment
Classifier: Framework :: Django
Classifier: Intended Audience :: Developers
Classifier: License :: OSI Approved :: MIT License
Classifier: Operating System :: OS Independent
Classifier: Programming Language :: Python
Classifier: Programming Language :: Python :: 3
Classifier: Programming Language :: Python :: 3 :: Only
Classifier: Programming Language :: Python :: 3.4
Classifier: Programming Language :: Python :: 3.5
Classifier: Programming Language :: Python :: 3.6
Classifier: Programming Language :: Python :: 3.7
Classifier: Topic :: Software Development :: Pre-processors
Requires-Dist: Django
Requires-Dist: Brotli (~=1.0.4)
Requires-Dist: zopfli (~=0.1.4)
Requires-Dist: yaspin (~=0.14.3)
